whitesource_common/__init__.py
whitesource_common/protocol.py
whitesource_common-0.2.0.dist-info/METADATA
whitesource_common-0.2.0.dist-info/WHEEL
whitesource_common-0.2.0.dist-info/top_level.txt
whitesource_common-0.2.0.dist-info/RECORD
