Metadata-Version: 2.1
Name: whitesource-common
Version: 0.2.0
Summary: common functions and models for whitesource
Home-page: UNKNOWN
License: UNKNOWN
Platform: UNKNOWN
Requires-Python: >=3.8.*
